distributions_abcdefg/Binomialdistribution.py
distributions_abcdefg/Gaussiandistribution.py
distributions_abcdefg/Generaldistribution.py
distributions_abcdefg/__init__.py
distributions_abcdefg-0.124.dist-info/METADATA
distributions_abcdefg-0.124.dist-info/WHEEL
distributions_abcdefg-0.124.dist-info/top_level.txt
distributions_abcdefg-0.124.dist-info/RECORD
