Metadata-Version: 2.1
Name: distributions-abcdefg
Version: 0.124
Summary: Gaussian distributions_abcdefg
